{
  "annotations": {
    "list": [
      {
        "builtIn": 1,
        "datasource": {
          "type": "grafana",
          "uid": "-- Grafana --"
        },
        "enable": true,
        "hide": true,
        "iconColor": "rgba(0, 211, 255, 1)",
        "name": "Annotations & Alerts",
        "type": "dashboard"
      }
    ]
  },
  "editable": true,
  "fiscalYearStartMonth": 0,
  "graphTooltip": 0,
  "id": 355,
  "links": [],
  "panels": [
    {
      "datasource": {
        "type": "influxdb",
        "uid": "bfm1e64dc8lq8b"
      },
      "fieldConfig": {
        "defaults": {
          "color": {
            "mode": "thresholds"
          },
          "mappings": [],
          "thresholds": {
            "mode": "absolute",
            "steps": [
              {
                "color": "green"
              },
              {
                "color": "red",
                "value": 80
              }
            ]
          }
        },
        "overrides": []
      },
      "gridPos": {
        "h": 37,
        "w": 24,
        "x": 0,
        "y": 0
      },
      "id": 1,
      "options": {
        "SVGBaseFix": true,
        "add100Percentage": true,
        "calcsMutation": "standard",
        "centerAlignContent": true,
        "codeData": "{\n  \"text\": \"Random text\"\n}",
        "css": "@import url('https://fonts.googleapis.com/css2?family=Orbitron:wght@500;700;800;900&display=swap');\r\n\r\n:root{\r\n  --bg: #060d18;\r\n  --bg2: #091425;\r\n  --panel: #071a34;\r\n  --panel2: #081a31;\r\n  --card: #07182d;\r\n  --line: rgba(73, 134, 255, 0.18);\r\n  --line-strong: rgba(73, 134, 255, 0.32);\r\n  --text: #f1f6ff;\r\n  --muted: #8ea7cc;\r\n  --green: #00e38c;\r\n  --green-d: #00b96f;\r\n  --red: #ff5f72;\r\n  --red-d: #d84057;\r\n  --yellow: #ffd348;\r\n  --blue: #4ea0ff;\r\n  --cyan: #5bc0ff;\r\n  --shadow: 0 0 0 1px rgba(255,255,255,0.02), 0 14px 30px rgba(0,0,0,0.35);\r\n  --radius-xl: 34px;\r\n  --radius-lg: 20px;\r\n  --radius-md: 14px;\r\n  --radius-sm: 10px;\r\n}\r\n\r\n*{\r\n  box-sizing: border-box;\r\n}\r\n\r\nhtml, body{\r\n  margin: 0;\r\n  padding: 0;\r\n  background:\r\n    radial-gradient(circle at top left, rgba(54,109,212,0.12), transparent 22%),\r\n    linear-gradient(180deg, #08111e 0%, #050b15 100%);\r\n  color: var(--text);\r\n  font-family: \"Orbitron\", sans-serif;\r\n}\r\n\r\n.caa-page{\r\n  width: 100%;\r\n  min-height: 100vh;\r\n  padding: clamp(6px, 0.6vw, 10px);\r\n  background: transparent;\r\n}\r\n\r\n.caa-shell{\r\n  width: 100%;\r\n  max-width: 100%;\r\n  border-radius: clamp(16px, 1.2vw, 26px);\r\n  border: 1px solid rgba(255,255,255,0.04);\r\n  background: linear-gradient(180deg, rgba(10,18,31,0.97), rgba(6,12,22,0.98));\r\n  box-shadow: var(--shadow);\r\n  padding: clamp(8px, 0.8vw, 14px);\r\n}\r\n\r\n/* header */\r\n.caa-header{\r\n  padding: clamp(4px, 0.4vw, 6px) clamp(6px, 0.5vw, 8px) clamp(10px, 0.9vw, 14px);\r\n}\r\n\r\n.caa-title{\r\n  text-align: center;\r\n  font-size: clamp(18px, 1.6vw, 28px);\r\n  font-weight: 900;\r\n  letter-spacing: clamp(0.5px, 0.08vw, 1.3px);\r\n  color: #ffffff;\r\n}\r\n\r\n/* layout */\r\n.caa-layout{\r\n  display: grid;\r\n  grid-template-columns: minmax(0, 1fr) clamp(260px, 20vw, 330px);\r\n  gap: clamp(8px, 0.8vw, 14px);\r\n}\r\n\r\n.caa-left{\r\n  display: flex;\r\n  flex-direction: column;\r\n  gap: clamp(10px, 1vw, 16px);\r\n}\r\n\r\n/* section */\r\n.system-section{\r\n  border-radius: 18px;\r\n  border: 1px solid var(--line);\r\n  background: linear-gradient(180deg, rgba(6,21,43,0.97), rgba(5,15,28,0.98));\r\n  box-shadow: var(--shadow);\r\n  padding: clamp(8px, 0.8vw, 12px);\r\n}\r\n\r\n.rounded-bottom{\r\n  border-radius: 28px;\r\n}\r\n\r\n.section-head{\r\n  display: flex;\r\n  align-items: center;\r\n  justify-content: space-between;\r\n  padding: 2px 2px clamp(8px, 0.8vw, 12px);\r\n}\r\n\r\n.section-title{\r\n  font-size: clamp(14px, 1vw, 18px);\r\n  font-weight: 900;\r\n  color: #ffffff;\r\n  letter-spacing: 0.8px;\r\n}\r\n\r\n.tank-grid{\r\n  display: grid;\r\n  gap: clamp(8px, 0.8vw, 12px);\r\n}\r\n\r\n.acid-grid{\r\n  grid-template-columns: repeat(4, minmax(0, 1fr));\r\n}\r\n\r\n.alk-grid{\r\n  grid-template-columns: repeat(3, minmax(0, 1fr));\r\n}\r\n\r\n/* tank card */\r\n.tank-card{\r\n  border-radius: 16px;\r\n  border: 1px solid rgba(83, 151, 255, 0.16);\r\n  background: linear-gradient(180deg, rgba(5,28,58,0.95), rgba(4,18,34,0.98));\r\n  box-shadow: inset 0 0 0 1px rgba(255,255,255,0.02);\r\n  padding: clamp(8px, 0.8vw, 12px);\r\n}\r\n\r\n.tank-card-head{\r\n  position: relative;\r\n  display: flex;\r\n  justify-content: center;\r\n  align-items: center;\r\n  margin-bottom: clamp(8px, 0.7vw, 10px);\r\n}\r\n\r\n.tank-name{\r\n  text-align: center;\r\n  width: 100%;\r\n  font-size: clamp(11px, 0.9vw, 15px);\r\n  font-weight: 900;\r\n  color: #ffffff;\r\n}\r\n\r\n.tank-sub{\r\n  font-size: 9px;\r\n  color: #a8bfdf;\r\n  letter-spacing: 0.5px;\r\n}\r\n\r\n.tank-badge{\r\n  position: absolute;\r\n  right: 0;\r\n  top: 0;\r\n  padding: 7px 12px;\r\n  border-radius: 999px;\r\n  font-size: 9px;\r\n  font-weight: 800;\r\n  letter-spacing: 0.6px;\r\n  white-space: nowrap;\r\n}\r\n\r\n.tank-badge.running{\r\n  background: linear-gradient(180deg, var(--green), var(--green-d));\r\n  color: #04140c;\r\n}\r\n\r\n.tank-badge.standby{\r\n  background: linear-gradient(180deg, #8193b1, #64758e);\r\n  color: #ffffff;\r\n}\r\n\r\n/* body */\r\n.tank-body{\r\n  display: grid;\r\n  grid-template-columns: clamp(100px, 9vw, 140px) 1fr;\r\n  gap: clamp(8px, 0.8vw, 12px);\r\n  align-items: center;\r\n}\r\n\r\n/* visual */\r\n.tank-visual-block{\r\n  display: flex;\r\n  align-items: center;\r\n  gap: clamp(5px, 0.5vw, 8px);\r\n}\r\n\r\n.tank-scale{\r\n  width: clamp(30px, 2.5vw, 42px);\r\n  height: clamp(130px, 11vw, 175px);\r\n  position: relative;\r\n}\r\n\r\n.tank-scale span{\r\n  position: absolute;\r\n  right: 0;\r\n  font-size: clamp(7px, 0.75vw, 9.5px);\r\n  color: #b9cff0;\r\n  font-weight: 700;\r\n}\r\n\r\n.tank-scale span:nth-child(1){\r\n  top: 0;\r\n}\r\n\r\n.tank-scale span:nth-child(2){\r\n  bottom: calc((80 / 560) * clamp(130px, 11vw, 175px) - 6px);\r\n}\r\n\r\n.tank-scale span:nth-child(3){\r\n  bottom: 0;\r\n  opacity: 0;\r\n}\r\n\r\n.tank-wrap{\r\n  display: flex;\r\n  align-items: center;\r\n  justify-content: center;\r\n}\r\n\r\n.tank{\r\n  position: relative;\r\n  width: clamp(68px, 5.5vw, 95px);\r\n  height: clamp(130px, 11vw, 175px);\r\n  border-radius: clamp(12px, 1vw, 18px);\r\n  border: 2px solid rgba(255,255,255,0.58);\r\n  background: linear-gradient(180deg, rgba(255,255,255,0.10), rgba(255,255,255,0.03));\r\n  overflow: hidden;\r\n  box-shadow: inset 0 0 20px rgba(255,255,255,0.04);\r\n}\r\n\r\n.tank-top-dash{\r\n  position: absolute;\r\n  top: 6px;\r\n  left: 10px;\r\n  right: 14px;\r\n  height: 6px;\r\n  border-top: 3px dashed rgba(20,28,44,0.95);\r\n  z-index: 5;\r\n}\r\n\r\n.tank-fill{\r\n  position: absolute;\r\n  left: 0;\r\n  right: 0;\r\n  bottom: 0;\r\n}\r\n\r\n.tank-fill.green-fill{\r\n  background: linear-gradient(180deg, #8be8b4 0%, #2fd97c 100%);\r\n}\r\n\r\n.tank-fill.red-fill{\r\n  background: linear-gradient(180deg, #ff8d8d 0%, #ff5d5d 100%);\r\n}\r\n\r\n.tank-center-value{\r\n  position: absolute;\r\n  left: 0;\r\n  right: 0;\r\n  top: 50%;\r\n  transform: translateY(-50%) rotate(-90deg);\r\n  text-align: center;\r\n  font-size: clamp(8px, 0.7vw, 11px);\r\n  font-weight: 900;\r\n  color: rgba(255,255,255,0.88);\r\n  z-index: 6;\r\n}\r\n\r\n.tank-zones{\r\n  position: absolute;\r\n  inset: 0;\r\n  z-index: 3;\r\n  pointer-events: none;\r\n}\r\n\r\n.zone{\r\n  position: absolute;\r\n  left: 6px;\r\n  font-size: clamp(7px, 0.65vw, 9px);\r\n  font-weight: 700;\r\n  color: rgba(255,255,255,0.72);\r\n}\r\n\r\n.zone.high{\r\n  top: 10px;\r\n}\r\n\r\n.zone.low{\r\n  bottom: 12px;\r\n}\r\n\r\n.tank-ruler{\r\n  position: absolute;\r\n  right: 6px;\r\n  top: 10px;\r\n  bottom: 8px;\r\n  width: clamp(9px, 0.8vw, 12px);\r\n  display: flex;\r\n  flex-direction: column;\r\n  justify-content: space-between;\r\n  z-index: 7;\r\n}\r\n\r\n.tank-ruler span{\r\n  display: block;\r\n  height: 4px;\r\n  background: rgba(240,245,255,0.75);\r\n  border-radius: 2px;\r\n}\r\n\r\n/* metrics */\r\n.tank-metrics{\r\n  display: grid;\r\n  grid-template-columns: repeat(2, 1fr);\r\n  gap: clamp(6px, 0.6vw, 8px);\r\n}\r\n\r\n.metric{\r\n  min-height: 58px;\r\n  height: clamp(46px, 4vw, 54px);\r\n  border-radius: 10px;\r\n  padding: 6px 12px;\r\n  border: 1px solid rgba(255,255,255,0.06);\r\n  background: rgba(255,255,255,0.02);\r\n  display: flex;\r\n  flex-direction: column;\r\n  justify-content: center;\r\n  gap: 3px;\r\n}\r\n\r\n.metric.good{\r\n  background: linear-gradient(145deg, #13443c, #0e6742);\r\n  color:#07c950;\r\n  border:1px solid #0e6742;\r\n  box-shadow: 0 0 10px rgba(7,201,80,0.18);\r\n}\r\n\r\n.metric.good span,\r\n.metric.good strong{\r\n  color:#07c950;\r\n}\r\n\r\n.metric.danger{\r\n  background: linear-gradient(145deg,#4a1f22,#7a2c34);\r\n  color:#ff5a66;\r\n  border:1px solid #8f3a44;\r\n  box-shadow:0 0 10px rgba(255,90,102,0.18);\r\n}\r\n\r\n.metric.danger span,\r\n.metric.danger strong{\r\n  color:#ff5a66;\r\n}\r\n\r\n.metric.neutral{\r\n  background:#1a2230;\r\n  border:1px solid #8a98b3;\r\n}\r\n\r\n.metric.neutral span,\r\n.metric.neutral strong{\r\n  color:#cfd8f6;\r\n}\r\n\r\n.metric.wide{\r\n  grid-column: span 2;\r\n}\r\n\r\n.metric span{\r\n  font-size: clamp(7px, 0.6vw, 9px) !important;\r\n  font-weight: 700;\r\n  letter-spacing: 0.4px;\r\n  margin: 0;\r\n}\r\n\r\n.metric strong{\r\n  font-size: clamp(11px, 0.95vw, 16px) !important;\r\n  font-weight: 900;\r\n  margin: 0;\r\n}\r\n\r\n/* alarm panel */\r\n.alarm-panel{\r\n  border-radius: 18px;\r\n  border: 1px solid var(--line);\r\n  background:\r\n    radial-gradient(circle at top left, rgba(78,160,255,0.08), transparent 26%),\r\n    linear-gradient(180deg, rgba(7,18,33,0.98), rgba(5,12,22,0.98));\r\n  box-shadow: var(--shadow);\r\n  padding: clamp(10px, 0.8vw, 14px);\r\n  display: flex;\r\n  flex-direction: column;\r\n  min-height: 100%;\r\n}\r\n\r\n/* header */\r\n.alarm-panel-header{\r\n  display: flex;\r\n  justify-content: space-between;\r\n  align-items: center;\r\n  margin-bottom: 14px;\r\n}\r\n\r\n.alarm-panel-title{\r\n  font-size: clamp(14px, 1vw, 18px);\r\n  font-weight: 900;\r\n  color: #ffffff;\r\n  letter-spacing: 0.5px;\r\n}\r\n\r\n.alarm-live-pill{\r\n  padding: 5px 10px;\r\n  border-radius: 999px;\r\n  font-size: 8px;\r\n  font-weight: 800;\r\n  letter-spacing: 0.8px;\r\n  color: #7fd8ff;\r\n  border: 1px solid rgba(91,192,255,0.30);\r\n  background: rgba(91,192,255,0.08);\r\n  box-shadow: 0 0 10px rgba(91,192,255,0.10);\r\n}\r\n\r\n/* summary */\r\n.alarm-summary{\r\n  display: grid;\r\n  grid-template-columns: repeat(3, 1fr);\r\n  gap: clamp(8px, 0.6vw, 10px);\r\n  margin-bottom: 14px;\r\n}\r\n\r\n.summary-box{\r\n  min-height: clamp(62px, 5vw, 78px);\r\n  border-radius: 14px;\r\n  padding: 10px;\r\n  border: 1px solid rgba(255,255,255,0.06);\r\n  background: linear-gradient(180deg, rgba(255,255,255,0.03), rgba(255,255,255,0.015));\r\n  display: flex;\r\n  flex-direction: column;\r\n  align-items: center;\r\n  justify-content: center;\r\n  position: relative;\r\n  overflow: hidden;\r\n}\r\n\r\n.summary-box::before{\r\n  content:\"\";\r\n  position:absolute;\r\n  inset:0;\r\n  background: linear-gradient(180deg, rgba(255,255,255,0.04), transparent 40%);\r\n  pointer-events:none;\r\n}\r\n\r\n.summary-label{\r\n  font-size: 8px;\r\n  margin-bottom: 6px;\r\n  color: #dce8fa;\r\n  letter-spacing: 0.7px;\r\n}\r\n\r\n.summary-value{\r\n  font-size: clamp(22px, 1.8vw, 30px);\r\n  line-height: 1;\r\n  font-weight: 900;\r\n  color: #ffffff;\r\n}\r\n\r\n.summary-box.critical{\r\n  border-color: rgba(255,95,114,0.34);\r\n  box-shadow: inset 0 0 18px rgba(255,95,114,0.05), 0 0 14px rgba(255,95,114,0.08);\r\n}\r\n\r\n.summary-box.warning{\r\n  border-color: rgba(255,211,72,0.34);\r\n  box-shadow: inset 0 0 18px rgba(255,211,72,0.05), 0 0 14px rgba(255,211,72,0.06);\r\n}\r\n\r\n.summary-box.info{\r\n  border-color: rgba(78,160,255,0.34);\r\n  box-shadow: inset 0 0 18px rgba(78,160,255,0.05), 0 0 14px rgba(78,160,255,0.06);\r\n}\r\n\r\n/* featured critical */\r\n.featured-alarm{\r\n  border-radius: 16px;\r\n  padding: 14px;\r\n  margin-bottom: 14px;\r\n  position: relative;\r\n  overflow: hidden;\r\n  border: 1px solid rgba(255,255,255,0.08);\r\n}\r\n\r\n.featured-alarm::before{\r\n  content:\"\";\r\n  position:absolute;\r\n  inset:0;\r\n  background: linear-gradient(180deg, rgba(255,255,255,0.04), transparent 42%);\r\n  pointer-events:none;\r\n}\r\n\r\n.featured-alarm.critical{\r\n  border-color: rgba(255,95,114,0.38);\r\n  background:\r\n    radial-gradient(circle at top right, rgba(255,95,114,0.10), transparent 30%),\r\n    linear-gradient(180deg, rgba(65,15,24,0.55), rgba(22,11,19,0.85));\r\n  box-shadow:\r\n    inset 0 0 24px rgba(255,95,114,0.05),\r\n    0 0 18px rgba(255,95,114,0.08);\r\n}\r\n\r\n.featured-top{\r\n  display: flex;\r\n  justify-content: space-between;\r\n  align-items: center;\r\n  margin-bottom: 10px;\r\n}\r\n\r\n.featured-tag{\r\n  font-size: 8px;\r\n  letter-spacing: 0.9px;\r\n  color: #ffb3bc;\r\n}\r\n\r\n.featured-time{\r\n  font-size: 9px;\r\n  color: #ffd6dc;\r\n}\r\n\r\n.featured-title{\r\n  font-size: clamp(11px, 0.9vw, 14px);\r\n  font-weight: 900;\r\n  color: #ffffff;\r\n  line-height: 1.4;\r\n  margin-bottom: 8px;\r\n}\r\n\r\n.featured-sub{\r\n  font-size: 9px;\r\n  color: #f0c9d0;\r\n  line-height: 1.45;\r\n}\r\n\r\n/* timeline title */\r\n.alarm-timeline-label{\r\n  font-size: 8px;\r\n  color: #8ea7cc;\r\n  letter-spacing: 1px;\r\n  margin-bottom: 10px;\r\n}\r\n\r\n/* list */\r\n.alarm-list{\r\n  display: flex;\r\n  flex-direction: column;\r\n  gap: 12px;\r\n}\r\n\r\n.alarm-item{\r\n  min-height: 78px;\r\n  border-radius: 16px;\r\n  border: 1px solid rgba(255,255,255,0.06);\r\n  background:\r\n    linear-gradient(180deg, rgba(255,255,255,0.028), rgba(255,255,255,0.012));\r\n  display: grid;\r\n  grid-template-columns: 6px 1fr;\r\n  overflow: hidden;\r\n  transition: transform 0.15s ease, box-shadow 0.15s ease;\r\n}\r\n\r\n.alarm-item:hover{\r\n  transform: translateY(-1px);\r\n}\r\n\r\n.alarm-rail{\r\n  height: 100%;\r\n}\r\n\r\n.alarm-item.critical .alarm-rail{\r\n  background: linear-gradient(180deg, #ff5f72, #d84057);\r\n}\r\n\r\n.alarm-item.warning .alarm-rail{\r\n  background: linear-gradient(180deg, #ffd348, #d8ae22);\r\n}\r\n\r\n.alarm-item.info .alarm-rail{\r\n  background: linear-gradient(180deg, #4ea0ff, #2d7fe1);\r\n}\r\n\r\n.alarm-item.neutral .alarm-rail{\r\n  background: linear-gradient(180deg, #95a3bb, #6e7c95);\r\n}\r\n\r\n.alarm-item.critical{\r\n  box-shadow: 0 0 14px rgba(255,95,114,0.06);\r\n}\r\n\r\n.alarm-item.warning{\r\n  box-shadow: 0 0 14px rgba(255,211,72,0.05);\r\n}\r\n\r\n.alarm-item.info{\r\n  box-shadow: 0 0 14px rgba(78,160,255,0.05);\r\n}\r\n\r\n.alarm-item.neutral{\r\n  box-shadow: 0 0 14px rgba(149,163,187,0.04);\r\n}\r\n\r\n.alarm-content{\r\n  padding: 12px 14px;\r\n  display: flex;\r\n  flex-direction: column;\r\n  justify-content: center;\r\n}\r\n\r\n.alarm-row-top{\r\n  display: flex;\r\n  align-items: center;\r\n  justify-content: space-between;\r\n  gap: 10px;\r\n  margin-bottom: 10px;\r\n}\r\n\r\n.alarm-severity-wrap{\r\n  display: flex;\r\n  align-items: center;\r\n  gap: 8px;\r\n}\r\n\r\n.alarm-dot{\r\n  width: 8px;\r\n  height: 8px;\r\n  border-radius: 50%;\r\n  background: currentColor;\r\n  flex: 0 0 8px;\r\n}\r\n\r\n.alarm-item.critical .alarm-dot{\r\n  color: #ff5f72;\r\n  box-shadow: 0 0 8px rgba(255,95,114,0.45);\r\n}\r\n\r\n.alarm-item.warning .alarm-dot{\r\n  color: #ffd348;\r\n  box-shadow: 0 0 8px rgba(255,211,72,0.35);\r\n}\r\n\r\n.alarm-item.info .alarm-dot{\r\n  color: #4ea0ff;\r\n  box-shadow: 0 0 8px rgba(78,160,255,0.35);\r\n}\r\n\r\n.alarm-item.neutral .alarm-dot{\r\n  color: #95a3bb;\r\n}\r\n\r\n.alarm-severity{\r\n  font-size: 8px;\r\n  font-weight: 800;\r\n  letter-spacing: 0.7px;\r\n  color: #ffffff;\r\n  padding: 4px 8px;\r\n  border-radius: 999px;\r\n  border: 1px solid rgba(255,255,255,0.06);\r\n  background: rgba(255,255,255,0.04);\r\n}\r\n\r\n.alarm-item.critical .alarm-severity{\r\n  color: #ffb6c0;\r\n  border-color: rgba(255,95,114,0.25);\r\n  background: rgba(255,95,114,0.08);\r\n}\r\n\r\n.alarm-item.warning .alarm-severity{\r\n  color: #ffe27c;\r\n  border-color: rgba(255,211,72,0.22);\r\n  background: rgba(255,211,72,0.08);\r\n}\r\n\r\n.alarm-item.info .alarm-severity{\r\n  color: #8fccff;\r\n  border-color: rgba(78,160,255,0.22);\r\n  background: rgba(78,160,255,0.08);\r\n}\r\n\r\n.alarm-item.neutral .alarm-severity{\r\n  color: #c7d4e8;\r\n  border-color: rgba(149,163,187,0.18);\r\n  background: rgba(149,163,187,0.08);\r\n}\r\n\r\n.alarm-time{\r\n  font-size: 9px;\r\n  color: #b7c9e6;\r\n  white-space: nowrap;\r\n  padding: 3px 7px;\r\n  border-radius: 999px;\r\n  background: rgba(255,255,255,0.04);\r\n}\r\n\r\n.alarm-msg{\r\n  font-size: clamp(9px, 0.75vw, 11px);\r\n  color: #ffffff;\r\n  line-height: 1.45;\r\n  font-weight: 700;\r\n}\r\n\r\n/* responsive */\r\n@media (max-width: 1600px){\r\n  .acid-grid{\r\n    grid-template-columns: repeat(2, 1fr);\r\n  }\r\n\r\n  .alk-grid{\r\n    grid-template-columns: repeat(2, 1fr);\r\n  }\r\n}\r\n\r\n@media (max-width: 1200px){\r\n  .caa-layout{\r\n    grid-template-columns: 1fr;\r\n  }\r\n\r\n  .acid-grid,\r\n  .alk-grid{\r\n    grid-template-columns: repeat(2, 1fr);\r\n  }\r\n}\r\n\r\n@media (max-width: 900px){\r\n  .acid-grid,\r\n  .alk-grid{\r\n    grid-template-columns: 1fr;\r\n  }\r\n\r\n  .tank-body{\r\n    grid-template-columns: 1fr;\r\n  }\r\n\r\n  .tank-visual-block{\r\n    justify-content: center;\r\n  }\r\n\r\n  .caa-title{\r\n    font-size: 20px;\r\n  }\r\n}\r\n\r\n.trend-section{\r\n  margin-top: 14px;\r\n}\r\n\r\n.trend-grid{\r\n  display: grid;\r\n  grid-template-columns: repeat(2, minmax(0, 1fr));\r\n  gap: 14px;\r\n}\r\n\r\n.trend-card{\r\n  border-radius: 18px;\r\n  border: 1px solid var(--line);\r\n  background: linear-gradient(180deg, rgba(6,21,43,0.97), rgba(5,15,28,0.98));\r\n  box-shadow: var(--shadow);\r\n  padding: 12px;\r\n  min-height: 250px;\r\n}\r\n\r\n.trend-header{\r\n  display: flex;\r\n  justify-content: space-between;\r\n  align-items: center;\r\n  gap: 10px;\r\n  margin-bottom: 10px;\r\n}\r\n\r\n.trend-title{\r\n  font-size: 13px;\r\n  font-weight: 900;\r\n  color: #ffffff;\r\n  letter-spacing: 0.5px;\r\n}\r\n\r\n.trend-last{\r\n  font-size: 10px;\r\n  font-weight: 800;\r\n  color: #07c950;\r\n  padding: 5px 10px;\r\n  border-radius: 999px;\r\n  border: 1px solid #0e6742;\r\n  background: linear-gradient(145deg, #13443c, #0e6742);\r\n}\r\n\r\n.trend-last.danger{\r\n  color: #ff5a66;\r\n  border: 1px solid #8f3a44;\r\n  background: linear-gradient(145deg,#4a1f22,#7a2c34);\r\n}\r\n\r\n.trend-chart{\r\n  width: 100%;\r\n  height: 190px;\r\n  border-radius: 14px;\r\n  border: 1px solid rgba(255,255,255,0.05);\r\n  background:\r\n    linear-gradient(180deg, rgba(255,255,255,0.02), rgba(255,255,255,0.01));\r\n  position: relative;\r\n  overflow: hidden;\r\n}\r\n\r\n.trend-svg{\r\n  width: 100%;\r\n  height: 100%;\r\n  display: block;\r\n}\r\n\r\n.limit-high,\r\n.limit-low{\r\n  stroke-width: 2;\r\n  stroke-dasharray: 6 5;\r\n}\r\n\r\n.limit-high{\r\n  stroke: rgba(255,95,114,0.85);\r\n}\r\n\r\n.limit-low{\r\n  stroke: rgba(120,170,255,0.75);\r\n}\r\n\r\n.limit-label{\r\n  font-size: 11px;\r\n  font-family: \"Orbitron\", sans-serif;\r\n  font-weight: 700;\r\n  letter-spacing: 0.5px;\r\n}\r\n\r\n.high-label{\r\n  fill: #ff8b99;\r\n}\r\n\r\n.low-label{\r\n  fill: #8fc8ff;\r\n}\r\n\r\n.trend-line{\r\n  stroke-width: 3;\r\n  stroke-linecap: round;\r\n  stroke-linejoin: round;\r\n}\r\n\r\n.acid-line{\r\n  stroke: #5bc0ff;\r\n  filter: drop-shadow(0 0 4px rgba(91,192,255,0.35));\r\n}\r\n\r\n.alk-line{\r\n  stroke: #07c950;\r\n  filter: drop-shadow(0 0 4px rgba(7,201,80,0.30));\r\n}\r\n\r\n.danger-trend{\r\n  stroke: #ff5a66;\r\n  filter: drop-shadow(0 0 4px rgba(255,90,102,0.35));\r\n}\r\n\r\n.trend-point{\r\n  stroke: #ffffff;\r\n  stroke-width: 1.5;\r\n}\r\n\r\n.acid-point{\r\n  fill: #5bc0ff;\r\n}\r\n\r\n.alk-point{\r\n  fill: #07c950;\r\n}\r\n\r\n.danger-point{\r\n  fill: #ff5a66;\r\n}\r\n\r\n.tank-center-value {\r\n  display: none;\r\n}",
        "dynamicData": false,
        "dynamicFieldDisplayValues": false,
        "dynamicHtmlGraphics": false,
        "dynamicProps": false,
        "html": "<div class=\"caa-page\">\r\n  <div class=\"caa-shell\">\r\n\r\n    <!-- HEADER -->\r\n    <div class=\"caa-header\">\r\n      <div class=\"caa-title\">CENTRALISED ACID &amp; ALKALINE DETAIL DASHBOARD</div>\r\n    </div>\r\n\r\n    <div class=\"caa-layout\">\r\n\r\n      <!-- LEFT CONTENT -->\r\n      <div class=\"caa-left\">\r\n\r\n        <!-- ACID SYSTEM -->\r\n        <section class=\"system-section\">\r\n          <div class=\"section-head\">\r\n            <div class=\"section-title\">ACID SYSTEM</div>\r\n          </div>\r\n\r\n          <div class=\"tank-grid acid-grid\">\r\n\r\n            <!-- DILUTED ACID T1 -->\r\n            <div class=\"tank-card\">\r\n              <div class=\"tank-card-head\">\r\n                <div>\r\n                  <div class=\"tank-name\">DILUTED ACID T1</div>\r\n                  \r\n                </div>\r\n                <div class=\"tank-badge running\"></div>\r\n              </div>\r\n\r\n              <div class=\"tank-body\">\r\n                <div class=\"tank-visual-block\">\r\n                  <div class=\"tank-scale\">\r\n                    <span>560 cm</span>\r\n                    <span>80 cm</span>\r\n                    <span>0 cm</span>\r\n                  </div>\r\n\r\n                  <div class=\"tank-wrap\">\r\n                    <div class=\"tank\">\r\n                      <div class=\"tank-top-dash\"></div>\r\n                      <div class=\"tank-fill green-fill\" style=\"height: ;\"></div>\r\n                      <div class=\"tank-zones\">\r\n                        <span class=\"zone high\">HIGH</span>\r\n                        <span class=\"zone low\">LOW</span>\r\n                      </div>\r\n                      \r\n                      <div class=\"tank-ruler\">\r\n                        <span></span><span></span><span></span><span></span><span></span>\r\n                        <span></span><span></span><span></span><span></span><span></span>\r\n                      </div>\r\n                    </div>\r\n                  </div>\r\n                </div>\r\n\r\n                <div class=\"tank-metrics\">                 \r\n                  <div class=\"metric good\"><span>PUMP SPEED</span><strong>50 Hz</strong></div>\r\n                  <div class=\"metric good\"><span>ACID STRENGTH</span><strong>2.54</strong></div>\r\n                  <div class=\"metric good\"><span>LEVEL</span><strong>420 CM</strong></div>\r\n                  <div class=\"metric good\"><span>STATUS</span><strong>SUPPLYING</strong></div>\r\n                </div>\r\n              </div>\r\n            </div>\r\n\r\n            <!-- DILUTED ACID T2 -->\r\n            <div class=\"tank-card\">\r\n              <div class=\"tank-card-head\">\r\n                <div>\r\n                  <div class=\"tank-name\">DILUTED ACID T2</div>\r\n                  \r\n                </div>\r\n                \r\n              </div>\r\n\r\n              <div class=\"tank-body\">\r\n                <div class=\"tank-visual-block\">\r\n                  <div class=\"tank-scale\">\r\n                    <span>560 cm</span>\r\n                    <span>80 cm</span>\r\n                    <span>0 cm</span>\r\n                  </div>\r\n\r\n                  <div class=\"tank-wrap\">\r\n                    <div class=\"tank\">\r\n                      <div class=\"tank-top-dash\"></div>\r\n                      <div class=\"tank-fill red-fill\" style=\"height: ;\"></div>\r\n                      <div class=\"tank-zones\">\r\n                        <span class=\"zone high\">HIGH</span>\r\n                        <span class=\"zone low\">LOW</span>\r\n                      </div>\r\n                      <div class=\"tank-center-value\"></div>\r\n                      <div class=\"tank-ruler\">\r\n                        <span></span><span></span><span></span><span></span><span></span>\r\n                        <span></span><span></span><span></span><span></span><span></span>\r\n                      </div>\r\n                    </div>\r\n                  </div>\r\n                </div>\r\n\r\n                <div class=\"tank-metrics\">\r\n                  <div class=\"metric good\"><span>PUMP SPEED</span><strong>50 Hz</strong></div>\r\n                  <div class=\"metric danger\"><span>ACID STRENGTH</span><strong>2.94</strong></div>\r\n                  <div class=\"metric danger\"><span>LEVEL</span><strong>80 CM</strong></div>\r\n                  <div class=\"metric neutral\"><span>STATUS</span><strong>STANDBY</strong></div>\r\n                </div>\r\n              </div>\r\n            </div>\r\n\r\n            <!-- CONCENTRATED ACID T1 -->\r\n            <div class=\"tank-card\">\r\n              <div class=\"tank-card-head\">\r\n                <div>\r\n                  <div class=\"tank-name\">CONCENTRATED ACID T1</div>\r\n                  \r\n                </div>\r\n\r\n              </div>\r\n\r\n              <div class=\"tank-body\">\r\n                <div class=\"tank-visual-block\">\r\n                  <div class=\"tank-scale\">\r\n                    <span>560 cm</span>\r\n                    <span>80 cm</span>\r\n                    <span>0 cm</span>\r\n                  </div>\r\n\r\n                  <div class=\"tank-wrap\">\r\n                    <div class=\"tank\">\r\n                      <div class=\"tank-top-dash\"></div>\r\n                      <div class=\"tank-fill red-fill\" style=\"height: ;\"></div>\r\n                      <div class=\"tank-zones\">\r\n                        <span class=\"zone high\">HIGH</span>\r\n                        <span class=\"zone low\">LOW</span>\r\n                      </div>\r\n                      <div class=\"tank-center-value\"></div>\r\n                      <div class=\"tank-ruler\">\r\n                        <span></span><span></span><span></span><span></span><span></span>\r\n                        <span></span><span></span><span></span><span></span><span></span>\r\n                      </div>\r\n                    </div>\r\n                  </div>\r\n                </div>\r\n\r\n                <div class=\"tank-metrics compact-5\">                  \r\n                  <div class=\"metric good\"><span>PUMP SPEED</span><strong>50 Hz</strong></div>\r\n                  <div class=\"metric good\"><span>STATUS</span><strong>SUPPLYING</strong></div>\r\n                  <div class=\"metric danger wide\"><span>LEVEL</span><strong>80 CM</strong></div>\r\n                </div>\r\n              </div>\r\n            </div>\r\n\r\n            <!-- CONCENTRATED ACID T2 -->\r\n            <div class=\"tank-card\">\r\n              <div class=\"tank-card-head\">\r\n                <div>\r\n                  <div class=\"tank-name\">CONCENTRATED ACID T2</div>\r\n                  \r\n                </div>\r\n\r\n              </div>\r\n\r\n              <div class=\"tank-body\">\r\n                <div class=\"tank-visual-block\">\r\n                  <div class=\"tank-scale\">\r\n                    <span>560 cm</span>\r\n                    <span>80 cm</span>\r\n                    <span>80 cm</span>\r\n                  </div>\r\n\r\n                  <div class=\"tank-wrap\">\r\n                    <div class=\"tank\">\r\n                      <div class=\"tank-top-dash\"></div>\r\n                      <div class=\"tank-fill green-fill\" style=\"height: ;\"></div>\r\n                      <div class=\"tank-zones\">\r\n                        <span class=\"zone high\">HIGH</span>\r\n                        <span class=\"zone low\">LOW</span>\r\n                      </div>\r\n                      <div class=\"tank-center-value\"></div>\r\n                      <div class=\"tank-ruler\">\r\n                        <span></span><span></span><span></span><span></span><span></span>\r\n                        <span></span><span></span><span></span><span></span><span></span>\r\n                      </div>\r\n                    </div>\r\n                  </div>\r\n                </div>\r\n\r\n                <div class=\"tank-metrics compact-5\">                  \r\n                  <div class=\"metric good\"><span>PUMP SPEED</span><strong>50 Hz</strong></div>\r\n                  <div class=\"metric good\"><span>STATUS</span><strong>SUPPLYING</strong></div>\r\n                  <div class=\"metric good wide\"><span>LEVEL</span><strong>450 CM</strong></div>\r\n                </div>\r\n              </div>\r\n            </div>\r\n\r\n          </div>\r\n        </section>\r\n\r\n        <!-- ALKALINE SYSTEM -->\r\n        <section class=\"system-section rounded-bottom\">\r\n          <div class=\"section-head\">\r\n            <div class=\"section-title\">ALKALINE SYSTEM</div>\r\n          </div>\r\n\r\n          <div class=\"tank-grid alk-grid\">\r\n\r\n            <!-- DILUTED ALKALINE T1 -->\r\n            <div class=\"tank-card\">\r\n              <div class=\"tank-card-head\">\r\n                <div>\r\n                  <div class=\"tank-name\">DILUTED ALKALINE T1</div>\r\n                  \r\n                </div>\r\n\r\n              </div>\r\n\r\n              <div class=\"tank-body\">\r\n                <div class=\"tank-visual-block\">\r\n                  <div class=\"tank-scale\">\r\n                    <span>560 cm</span>\r\n                    <span>80 cm</span>\r\n                    <span>0 cm</span>\r\n                  </div>\r\n\r\n                  <div class=\"tank-wrap\">\r\n                    <div class=\"tank\">\r\n                      <div class=\"tank-top-dash\"></div>\r\n                      <div class=\"tank-fill green-fill\" style=\"height: ;\"></div>\r\n                      <div class=\"tank-zones\">\r\n                        <span class=\"zone high\">HIGH</span>\r\n                        <span class=\"zone low\">LOW</span>\r\n                      </div>\r\n                      <div class=\"tank-center-value\"></div>\r\n                      <div class=\"tank-ruler\">\r\n                        <span></span><span></span><span></span><span></span><span></span>\r\n                        <span></span><span></span><span></span><span></span><span></span>\r\n                      </div>\r\n                    </div>\r\n                  </div>\r\n                </div>\r\n\r\n                <div class=\"tank-metrics\">                  \r\n                  <div class=\"metric good\"><span>PUMP SPEED</span><strong>50 Hz</strong></div>\r\n                  <div class=\"metric good\"><span>ALKALINE STRENGTH %</span><strong>2.54</strong></div>\r\n                  <div class=\"metric good\"><span>LEVEL</span><strong>200 CM</strong></div>\r\n                  <div class=\"metric good\"><span>STATUS</span><strong>SUPPLYING</strong></div>\r\n                </div>\r\n              </div>\r\n            </div>\r\n\r\n            <!-- DILUTED ALKALINE T2 -->\r\n            <div class=\"tank-card\">\r\n              <div class=\"tank-card-head\">\r\n                <div>\r\n                  <div class=\"tank-name\">DILUTED ALKALINE T2</div>\r\n                  \r\n                </div>\r\n\r\n              </div>\r\n\r\n              <div class=\"tank-body\">\r\n                <div class=\"tank-visual-block\">\r\n                  <div class=\"tank-scale\">\r\n                    <span>560 cm</span>\r\n                    <span>80 cm</span>\r\n                    <span>0 cm</span>\r\n                  </div>\r\n\r\n                  <div class=\"tank-wrap\">\r\n                    <div class=\"tank\">\r\n                      <div class=\"tank-top-dash\"></div>\r\n                      <div class=\"tank-fill green-fill\" style=\"height: ;\"></div>\r\n                      <div class=\"tank-zones\">\r\n                        <span class=\"zone high\">HIGH</span>\r\n                        <span class=\"zone low\">LOW</span>\r\n                      </div>\r\n                      <div class=\"tank-center-value\"></div>\r\n                      <div class=\"tank-ruler\">\r\n                        <span></span><span></span><span></span><span></span><span></span>\r\n                        <span></span><span></span><span></span><span></span><span></span>\r\n                      </div>\r\n                    </div>\r\n                  </div>\r\n                </div>\r\n\r\n                <div class=\"tank-metrics\">                 \r\n                  <div class=\"metric good\"><span>PUMP SPEED</span><strong>50 Hz</strong></div>\r\n                  <div class=\"metric danger\"><span>ALKALINE STRENGTH %</span><strong>2.94</strong></div>\r\n                  <div class=\"metric good\"><span>LEVEL</span><strong>120 CM</strong></div>\r\n                  <div class=\"metric neutral\"><span>STATUS</span><strong>STANDBY</strong></div>\r\n                </div>\r\n              </div>\r\n            </div>\r\n\r\n            <!-- CONCENTRATED ALKALINE T1 -->\r\n            <div class=\"tank-card\">\r\n              <div class=\"tank-card-head\">\r\n                <div>\r\n                  <div class=\"tank-name\">CONCENTRATED ALKALINE T1</div>\r\n                  \r\n                </div>\r\n\r\n              </div>\r\n\r\n              <div class=\"tank-body\">\r\n                <div class=\"tank-visual-block\">\r\n                  <div class=\"tank-scale\">\r\n                    <span>560 cm</span>\r\n                    <span>80 cm</span>\r\n                    <span>0 cm</span>\r\n                  </div>\r\n\r\n                  <div class=\"tank-wrap\">\r\n                    <div class=\"tank\">\r\n                      <div class=\"tank-top-dash\"></div>\r\n                      <div class=\"tank-fill green-fill\" style=\"height: ;\"></div>\r\n                      <div class=\"tank-zones\">\r\n                        <span class=\"zone high\">HIGH</span>\r\n                        <span class=\"zone low\">LOW</span>\r\n                      </div>\r\n                      <div class=\"tank-center-value\"></div>\r\n                      <div class=\"tank-ruler\">\r\n                        <span></span><span></span><span></span><span></span><span></span>\r\n                        <span></span><span></span><span></span><span></span><span></span>\r\n                      </div>\r\n                    </div>\r\n                  </div>\r\n                </div>\r\n\r\n                <div class=\"tank-metrics compact-5\">                  \r\n                  <div class=\"metric good\"><span>PUMP SPEED</span><strong>50 Hz</strong></div>\r\n                  <div class=\"metric good\"><span>STATUS</span><strong>SUPPLYING</strong></div>\r\n                  <div class=\"metric good wide\"><span>LEVEL</span><strong>120 CM</strong></div>\r\n                </div>\r\n              </div>\r\n            </div>\r\n\r\n          </div>\r\n        </section>\r\n\r\n        <div class=\"trend-section\">\r\n          <div class=\"trend-grid\">\r\n\r\n            <!-- ACID T1 -->\r\n            <div class=\"trend-card\">\r\n              <div class=\"trend-header\">\r\n                <div class=\"trend-title\">DILUTED ACID T1 - ACID STRENGTH TREND</div>\r\n                <div class=\"trend-last\">LAST: 2.54</div>\r\n              </div>\r\n              <div class=\"trend-chart\">\r\n                <svg viewBox=\"0 0 600 190\" class=\"trend-svg\" preserveAspectRatio=\"none\">\r\n                  <line x1=\"20\" y1=\"40\" x2=\"580\" y2=\"40\" class=\"limit-high\"/>\r\n                  <text x=\"24\" y=\"32\" class=\"limit-label high-label\">HIGH</text>\r\n\r\n                  <line x1=\"20\" y1=\"145\" x2=\"580\" y2=\"145\" class=\"limit-low\"/>\r\n                  <text x=\"24\" y=\"138\" class=\"limit-label low-label\">LOW</text>\r\n\r\n                  <polyline\r\n                    points=\"20,118 80,114 140,116 200,108 260,110 320,104 380,106 440,98 500,96 580,92\"\r\n                    class=\"trend-line acid-line\"\r\n                    fill=\"none\"\r\n                  />\r\n                  <circle cx=\"580\" cy=\"92\" r=\"4.5\" class=\"trend-point acid-point\"/>\r\n                </svg>\r\n              </div>\r\n            </div>\r\n\r\n            <!-- ACID T2 -->\r\n            <div class=\"trend-card\">\r\n              <div class=\"trend-header\">\r\n                <div class=\"trend-title\">DILUTED ACID T2 - ACID STRENGTH TREND</div>\r\n                <div class=\"trend-last danger\">LAST: 2.94</div>\r\n              </div>\r\n              <div class=\"trend-chart\">\r\n                <svg viewBox=\"0 0 600 190\" class=\"trend-svg\" preserveAspectRatio=\"none\">\r\n                  <line x1=\"20\" y1=\"40\" x2=\"580\" y2=\"40\" class=\"limit-high\"/>\r\n                  <text x=\"24\" y=\"32\" class=\"limit-label high-label\">HIGH</text>\r\n\r\n                  <line x1=\"20\" y1=\"145\" x2=\"580\" y2=\"145\" class=\"limit-low\"/>\r\n                  <text x=\"24\" y=\"138\" class=\"limit-label low-label\">LOW</text>\r\n\r\n                  <polyline\r\n                    points=\"20,110 80,108 140,104 200,100 260,95 320,88 380,84 440,76 500,70 580,64\"\r\n                    class=\"trend-line acid-line danger-trend\"\r\n                    fill=\"none\"\r\n                  />\r\n                  <circle cx=\"580\" cy=\"64\" r=\"4.5\" class=\"trend-point danger-point\"/>\r\n                </svg>\r\n              </div>\r\n            </div>\r\n\r\n            <!-- ALK T1 -->\r\n            <div class=\"trend-card\">\r\n              <div class=\"trend-header\">\r\n                <div class=\"trend-title\">DILUTED ALKALINE T1 - ALKALINE STRENGTH TREND</div>\r\n                <div class=\"trend-last\">LAST: 2.54</div>\r\n              </div>\r\n              <div class=\"trend-chart\">\r\n                <svg viewBox=\"0 0 600 190\" class=\"trend-svg\" preserveAspectRatio=\"none\">\r\n                  <line x1=\"20\" y1=\"40\" x2=\"580\" y2=\"40\" class=\"limit-high\"/>\r\n                  <text x=\"24\" y=\"32\" class=\"limit-label high-label\">HIGH</text>\r\n\r\n                  <line x1=\"20\" y1=\"145\" x2=\"580\" y2=\"145\" class=\"limit-low\"/>\r\n                  <text x=\"24\" y=\"138\" class=\"limit-label low-label\">LOW</text>\r\n\r\n                  <polyline\r\n                    points=\"20,122 80,120 140,118 200,116 260,112 320,108 380,106 440,102 500,98 580,94\"\r\n                    class=\"trend-line alk-line\"\r\n                    fill=\"none\"\r\n                  />\r\n                  <circle cx=\"580\" cy=\"94\" r=\"4.5\" class=\"trend-point alk-point\"/>\r\n                </svg>\r\n              </div>\r\n            </div>\r\n\r\n            <!-- ALK T2 -->\r\n            <div class=\"trend-card\">\r\n              <div class=\"trend-header\">\r\n                <div class=\"trend-title\">DILUTED ALKALINE T2 - ALKALINE STRENGTH TREND</div>\r\n                <div class=\"trend-last\">LAST: 2.94</div>\r\n              </div>\r\n              <div class=\"trend-chart\">\r\n                <svg viewBox=\"0 0 600 190\" class=\"trend-svg\" preserveAspectRatio=\"none\">\r\n                  <line x1=\"20\" y1=\"40\" x2=\"580\" y2=\"40\" class=\"limit-high\"/>\r\n                  <text x=\"24\" y=\"32\" class=\"limit-label high-label\">HIGH</text>\r\n\r\n                  <line x1=\"20\" y1=\"145\" x2=\"580\" y2=\"145\" class=\"limit-low\"/>\r\n                  <text x=\"24\" y=\"138\" class=\"limit-label low-label\">LOW</text>\r\n\r\n                  <polyline\r\n                    points=\"20,118 80,114 140,110 200,102 260,96 320,90 380,86 440,79 500,72 580,66\"\r\n                    class=\"trend-line alk-line\"\r\n                    fill=\"none\"\r\n                  />\r\n                  <circle cx=\"580\" cy=\"66\" r=\"4.5\" class=\"trend-point alk-point\"/>\r\n                </svg>\r\n              </div>\r\n            </div>\r\n\r\n          </div>\r\n        </div>\r\n      </div>\r\n\r\n      <aside class=\"alarm-panel\">\r\n        <div class=\"alarm-panel-header\">\r\n          <div class=\"alarm-panel-title\">ABNORMAL ALARM CAA</div>\r\n        </div>\r\n\r\n        <div class=\"alarm-summary\">\r\n          <div class=\"summary-box critical\">\r\n            <div class=\"summary-label\">CRITICAL</div>\r\n            <div class=\"summary-value\">0</div>\r\n          </div>\r\n          <div class=\"summary-box warning\">\r\n            <div class=\"summary-label\">WARNING</div>\r\n            <div class=\"summary-value\">0</div>\r\n          </div>\r\n          \r\n        </div>\r\n\r\n        <div class=\"featured-alarm critical\">\r\n          <div class=\"featured-top\">\r\n            <div class=\"featured-tag\">LATEST CRITICAL</div>\r\n            <div class=\"featured-time\">--</div>\r\n          </div>\r\n          <div class=\"featured-title\">--</div>\r\n\r\n        </div>\r\n\r\n        <div class=\"alarm-timeline-label\">ALARM TIMELINE</div>\r\n        <div class=\"alarm-list\"></div>\r\n\r\n        \r\n\r\n          \r\n         \r\n        </div>\r\n      </aside>\r\n\r\n    </div>\r\n  </div>\r\n</div>",
        "onInit": "// Sets the text from customProperties\nconst htmlgraphicsText = htmlNode.getElementById('htmlgraphics-text');\n\nif (htmlgraphicsText) {\n  htmlgraphicsText.textContent = customProperties.text;\n\n  // Change the text color based on the theme\n  if (theme.isDark) {\n    htmlgraphicsText.style.color = 'green';\n  } else {\n    htmlgraphicsText.style.color = 'red';\n  }\n}\n",
        "onInitOnResize": false,
        "onRender": "try {\n  const root = htmlNode;\n\n  function getSeries(refId) {\n    return (data.series || []).find(s => String(s.refId).toUpperCase() === refId);\n  }\n\n  function getSeriesAll(refId) {\n    return (data.series || []).filter(s => String(s.refId).toUpperCase() === refId);\n  }\n\n  function field(series, name) {\n    return series?.fields?.find(f => f.name === name) || null;\n  }\n\n  function arr(f) {\n    if (!f) return [];\n    if (f.values?.toArray) return f.values.toArray();\n    if (f.values?.buffer) return Array.from(f.values.buffer);\n    if (f.values?.get) {\n      let out = [];\n      for (let i = 0; i < f.values.length; i++) out.push(f.values.get(i));\n      return out;\n    }\n    return Array.isArray(f.values) ? f.values : [];\n  }\n\n  function resetAllCAAValues() {\n    root.querySelectorAll(\".tank-card .metric strong\").forEach(el => el.textContent = \"--\");\n    root.querySelectorAll(\".tank-card .metric\").forEach(m => {\n      m.classList.remove(\"good\", \"danger\");\n      m.classList.add(\"neutral\");\n    });\n    root.querySelectorAll(\".trend-last\").forEach(el => {\n      el.textContent = \"LAST: --\";\n      el.classList.remove(\"danger\");\n    });\n    root.querySelectorAll(\".trend-chart\").forEach(el => el.innerHTML = \"\");\n  }\n\n  resetAllCAAValues();\n\n  function setMetric(card, labelText, valueText, state = \"neutral\") {\n    if (!card) return;\n    const m = [...card.querySelectorAll(\".metric\")].find(x =>\n      String(x.querySelector(\"span\")?.textContent || \"\")\n        .toUpperCase()\n        .includes(labelText.toUpperCase())\n    );\n    if (!m) return;\n\n    m.classList.remove(\"good\", \"danger\", \"neutral\");\n    m.classList.add(state);\n\n    const strong = m.querySelector(\"strong\");\n    if (strong) strong.textContent = valueText;\n  }\n\n  function disableMetric(card, labelText) {\n    setMetric(card, labelText, \"--\", \"neutral\");\n  }\n\n  function greyUnusedMetric(card, labelText) {\n    if (!card) return;\n\n    const metric = [...card.querySelectorAll(\".metric\")].find(m =>\n      String(m.querySelector(\"span\")?.textContent || \"\")\n        .toUpperCase()\n        .includes(labelText.toUpperCase())\n    );\n\n    if (!metric) return;\n\n    metric.classList.remove(\"good\", \"danger\");\n    metric.classList.add(\"neutral\");\n\n    // CDS-style grey\n    metric.style.background = \"linear-gradient(180deg, #5f6979, #4f5968)\";\n    metric.style.border = \"1px solid #cfd6df\";\n    metric.style.boxShadow = \"none\";\n    metric.style.opacity = \"0.75\";\n\n    const span = metric.querySelector(\"span\");\n    const strong = metric.querySelector(\"strong\");\n\n    if (span) span.style.color = \"#d9dee6\";\n    if (strong) {\n      strong.textContent = \"--\";\n      strong.style.color = \"#f1f4f7\";\n    }\n  }\n\n  function disableTankCard(card) {\n    if (!card) return;\n    card.style.opacity = \"0.48\";\n\n    card.querySelectorAll(\".metric\").forEach(m => {\n      m.classList.remove(\"good\", \"danger\");\n      m.classList.add(\"neutral\");\n      const strong = m.querySelector(\"strong\");\n      if (strong) strong.textContent = \"--\";\n    });\n\n    const fill = card.querySelector(\".tank-fill\");\n    if (fill) {\n      fill.classList.remove(\"green-fill\", \"red-fill\");\n      fill.classList.add(\"red-fill\");\n      fill.style.height = \"0%\";\n      fill.style.opacity = \"0.35\";\n    }\n\n    const badge = card.querySelector(\".tank-badge\");\n    if (badge) {\n      badge.classList.remove(\"running\");\n      badge.classList.add(\"standby\");\n      badge.textContent = \"--\";\n    }\n  }\n\n  function getTankCard(titleText) {\n    return [...root.querySelectorAll(\".tank-card\")].find(card =>\n      String(card.querySelector(\".tank-name\")?.textContent || \"\")\n        .trim()\n        .toUpperCase() === titleText.toUpperCase()\n    );\n  }\n\n  const acidT1 = getTankCard(\"DILUTED ACID T1\");\n  const acidT2 = getTankCard(\"DILUTED ACID T2\");\n  const acidCon1 = getTankCard(\"CONCENTRATED ACID T1\");\n  const acidCon2 = getTankCard(\"CONCENTRATED ACID T2\");\n\n  const alkT1 = getTankCard(\"DILUTED ALKALINE T1\");\n  const alkT2 = getTankCard(\"DILUTED ALKALINE T2\");\n  const alkCon1 = getTankCard(\"CONCENTRATED ALKALINE T1\");\n\n\n  [acidCon1, acidCon2, alkCon1].forEach(card => {\n    if (!card) return;\n\n    card.style.opacity = \"1\";\n\n\n    card.querySelectorAll(\".metric\").forEach(m => {\n      m.classList.remove(\"good\", \"danger\");\n      m.classList.add(\"neutral\");\n      const strong = m.querySelector(\"strong\");\n      if (strong) strong.textContent = \"--\";\n    });\n\n\n    const fill = card.querySelector(\".tank-fill\");\n    if (fill) fill.style.opacity = \"1\";\n\n    const center = card.querySelector(\".tank-center-value\");\n    if (center) center.style.opacity = \"1\";\n  });\n\n  [\n    acidT1,\n    acidT2,\n    acidCon1,\n    acidCon2,\n    alkT1,\n    alkT2,\n    alkCon1\n  ].forEach(card => {\n    greyUnusedMetric(card, \"PUMP SPEED\");\n    greyUnusedMetric(card, \"STATUS\");\n  });\n\n  \n\n  const acidLatest = getSeries(\"A\");\n  const alkLatest = getSeries(\"C\");\n  const acidTrend = getSeriesAll(\"B\");\n  const alkTrend = getSeriesAll(\"D\");\n  const levelPressureLatest = getSeriesAll(\"E\");\n\n  function getLevelPressureMap(seriesInput) {\n    const seriesList = Array.isArray(seriesInput) ? seriesInput : [seriesInput];\n    const map = {};\n\n    seriesList.forEach(series => {\n      if (!series) return;\n\n      const valueField =\n        field(series, \"value\") ||\n        series.fields.find(f => f.type === \"number\");\n\n      if (!valueField) return;\n\n      const itemField = field(series, \"item\");\n      const values = arr(valueField);\n      const items = arr(itemField);\n\n      for (let i = 0; i < values.length; i++) {\n        let item = String(items[i] || \"\").toUpperCase();\n\n        if (!item) {\n          item = String(\n            valueField.labels?.item ||\n            valueField.config?.displayNameFromDS ||\n            series.name ||\n            \"\"\n          ).toUpperCase();\n        }\n\n        if (item.includes(\"CON_ACID_T1\")) item = \"CON_ACID_T1\";\n        if (item.includes(\"CON_ACID_T2\")) item = \"CON_ACID_T2\";\n        if (item.includes(\"DIL_ACID_T1\")) item = \"DIL_ACID_T1\";\n        if (item.includes(\"DIL_ACID_T2\")) item = \"DIL_ACID_T2\";\n        if (item.includes(\"CON_ALK_T1\")) item = \"CON_ALK_T1\";\n        if (item.includes(\"DIL_ALK_T1\")) item = \"DIL_ALK_T1\";\n        if (item.includes(\"DIL_ALK_T2\")) item = \"DIL_ALK_T2\";\n        if (item.includes(\"ACID_SUPPLY\")) item = \"ACID_SUPPLY\";\n        if (item.includes(\"ALK_SUPPLY\")) item = \"ALK_SUPPLY\";\n\n        if (item) map[item] = Number(values[i]);\n      }\n    });\n\n    return map;\n  }\n\n  function noDataTank(card) {\n    if (!card) return;\n\n    setMetric(card, \"LEVEL\", \"--\", \"neutral\");\n\n    const fill = card.querySelector(\".tank-fill\");\n    if (fill) {\n      fill.style.height = \"0%\";\n      fill.style.opacity = \"0.2\";\n      fill.classList.remove(\"green-fill\", \"red-fill\");\n    }\n  }\n\n  function applyLevel(card, levelValue) {\n    if (!card) return;\n\n    if (!Number.isFinite(levelValue)) {\n      noDataTank(card);\n      return;\n    }\n\n    const isLow = levelValue < 75;\n    if (isLow) {\n      const tankName = card.querySelector(\".tank-name\")?.textContent?.trim() || \"CAA TANK\";\n      addAlarm(\"critical\", `${tankName} - LEVEL LOW (${Math.round(levelValue)} CM)`);\n    }\n\n    setMetric(card, \"LEVEL\", `${Math.round(levelValue)} CM`, isLow ? \"danger\" : \"good\");\n\n    const fill = card.querySelector(\".tank-fill\");\n    if (fill) {\n      const pct = Math.max(0, Math.min(100, (levelValue / 560) * 100));\n      fill.style.height = `${pct}%`;\n      fill.style.opacity = \"1\";\n      fill.classList.remove(\"green-fill\", \"red-fill\");\n      fill.classList.add(isLow ? \"red-fill\" : \"green-fill\");\n    }\n  }\n\n  let alarmListData = [];\n\n  function addAlarm(type, message) {\n    alarmListData.push({\n      type,\n      message,\n      time: new Date().toLocaleTimeString(\"en-GB\", {\n        hour: \"2-digit\",\n        minute: \"2-digit\"\n      })\n    });\n  }\n\n  function renderCAAAlarms() {\n    const alarmPanel = root.querySelector(\".alarm-panel\");\n    if (!alarmPanel) return;\n\n    alarmPanel.style.opacity = \"1\";\n    alarmPanel.style.pointerEvents = \"auto\";\n\n    // remove INFO box\n    const infoBox = alarmPanel.querySelector(\".summary-box.info\");\n    if (infoBox) infoBox.style.display = \"none\";\n\n    const criticalCount = alarmListData.filter(a => a.type === \"critical\").length;\n    const warningCount = alarmListData.filter(a => a.type === \"warning\").length;\n\n    const criticalVal = alarmPanel.querySelector(\".summary-box.critical .summary-value\");\n    const warningVal = alarmPanel.querySelector(\".summary-box.warning .summary-value\");\n\n    if (criticalVal) criticalVal.textContent = criticalCount;\n    if (warningVal) warningVal.textContent = warningCount;\n\n    const featured = alarmPanel.querySelector(\".featured-title\");\n    const featuredTime = alarmPanel.querySelector(\".featured-time\");\n\n    const latestCritical = alarmListData.find(a => a.type === \"critical\");\n\n    if (featured) featured.textContent = latestCritical ? latestCritical.message : \"--\";\n    if (featuredTime) featuredTime.textContent = latestCritical ? latestCritical.time : \"--\";\n\n    const list = alarmPanel.querySelector(\".alarm-list\");\n    if (!list) return;\n\n    if (!alarmListData.length) {\n      list.innerHTML = `\n        <div class=\"alarm-item neutral\">\n          <div class=\"alarm-rail\"></div>\n          <div class=\"alarm-content\">\n            <div class=\"alarm-row-top\">\n              <div class=\"alarm-severity-wrap\">\n                <span class=\"alarm-dot\"></span>\n                <span class=\"alarm-severity\">--</span>\n              </div>\n              <div class=\"alarm-time\">--</div>\n            </div>\n            <div class=\"alarm-msg\">NO ACTIVE ALARM</div>\n          </div>\n        </div>\n      `;\n      return;\n    }\n\n    list.innerHTML = alarmListData.map(a => `\n      <div class=\"alarm-item ${a.type}\">\n        <div class=\"alarm-rail\"></div>\n        <div class=\"alarm-content\">\n          <div class=\"alarm-row-top\">\n            <div class=\"alarm-severity-wrap\">\n              <span class=\"alarm-dot\"></span>\n              <span class=\"alarm-severity\">${a.type === \"critical\" ? \"CRITICAL\" : \"WARNING\"}</span>\n            </div>\n            <div class=\"alarm-time\">${a.time}</div>\n          </div>\n          <div class=\"alarm-msg\">${a.message}</div>\n        </div>\n      </div>\n    `).join(\"\");\n  }\n\n  \n\n  function applyLatest(series, tankMap, valueFieldName) {\n    if (!series) return;\n\n    const tankField = field(series, \"tankNo\");\n    const valField = field(series, valueFieldName);\n    const minField = field(series, valueFieldName.replace(\"_current\", \"_min\"));\n    const maxField = field(series, valueFieldName.replace(\"_current\", \"_max\"));\n    const statusField = field(series, \"status\");\n\n    if (!valField) return;\n\n    const tanks = arr(tankField);\n    const vals = arr(valField);\n    const mins = arr(minField);\n    const maxs = arr(maxField);\n    const statuses = arr(statusField);\n\n    for (let i = 0; i < vals.length; i++) {\n      let tankNo = String(tanks[i] || \"\").toUpperCase();\n\n      if (!tankNo) {\n        tankNo = String(\n          valField.labels?.tankNo ||\n          valField.config?.displayNameFromDS ||\n          series.name ||\n          \"\"\n        ).toUpperCase();\n      }\n\n      const isAcid = valueFieldName.includes(\"acid\");\n      const isAlk = valueFieldName.includes(\"alkaline\");\n\n      if (tankNo === \"1\") tankNo = isAcid ? \"ACID1\" : isAlk ? \"ALK1\" : tankNo;\n      if (tankNo === \"2\") tankNo = isAcid ? \"ACID2\" : isAlk ? \"ALK2\" : tankNo;\n\n      if (tankNo.includes(\"ACID1\")) tankNo = \"ACID1\";\n      if (tankNo.includes(\"ACID2\")) tankNo = \"ACID2\";\n      if (tankNo.includes(\"ALK1\")) tankNo = \"ALK1\";\n      if (tankNo.includes(\"ALK2\")) tankNo = \"ALK2\";\n      const card = tankMap[tankNo];\n      if (!card) continue;\n\n      const val = Number(vals[i]);\n      const min = Number(mins[i]);\n      const max = Number(maxs[i]);\n      const status = Number(statuses[i]);\n\n      const bad = status === 2 || (\n        Number.isFinite(val) &&\n        Number.isFinite(min) &&\n        Number.isFinite(max) &&\n        (val < min || val > max)\n      );\n\n      if (bad) {\n        const tankName = card.querySelector(\".tank-name\")?.textContent?.trim() || \"CAA TANK\";\n        const label = valueFieldName.includes(\"acid\") ? \"ACID STRENGTH\" : \"ALKALINE STRENGTH\";\n\n        addAlarm(\n          \"warning\",\n          `${tankName} - ${label} OUT OF RANGE (${Number.isFinite(val) ? val.toFixed(2) : \"--\"})`\n        );\n      }\n\n      const ok = status === 1 && !bad;\n\n\n\n      setMetric(\n        card,\n        valueFieldName.includes(\"acid\") ? \"ACID STRENGTH\" : \"ALKALINE STRENGTH\",\n        Number.isFinite(val) ? val.toFixed(2) : \"--\",\n        bad ? \"danger\" : ok ? \"good\" : \"neutral\"\n      );\n\n      const fill = card.querySelector(\".tank-fill\");\n      if (fill) {\n        fill.classList.remove(\"green-fill\", \"red-fill\");\n        fill.classList.add(bad ? \"red-fill\" : \"green-fill\");\n        fill.style.height = \"0%\";\n        fill.style.opacity = \"0.35\";\n      }\n    }\n  }\n\n  applyLatest(acidLatest, { ACID1: acidT1, ACID2: acidT2 }, \"acid_current\");\n  applyLatest(alkLatest, { ALK1: alkT1, ALK2: alkT2 }, \"alkaline_current\");\n\n  const lp = getLevelPressureMap(levelPressureLatest);\n\n  applyLevel(acidCon1, lp.CON_ACID_T1);\n  applyLevel(acidCon2, lp.CON_ACID_T2);\n  applyLevel(acidT1, lp.DIL_ACID_T1);\n  applyLevel(acidT2, lp.DIL_ACID_T2);\n\n  applyLevel(alkCon1, lp.CON_ALK_T1);\n  applyLevel(alkT1, lp.DIL_ALK_T1);\n  applyLevel(alkT2, lp.DIL_ALK_T2);\n\n  function buildRows(seriesInput, valueKey, minKey, maxKey) {\n    const seriesList = Array.isArray(seriesInput) ? seriesInput : [seriesInput];\n    const out = {};\n\n    seriesList.forEach(series => {\n      if (!series) return;\n\n      const timeField =\n        field(series, \"_time\") ||\n        field(series, \"Time\") ||\n        series.fields.find(f => f.type === \"time\");\n\n      const valField = field(series, valueKey);\n      const minField = field(series, minKey);\n      const maxField = field(series, maxKey);\n      const tankField = field(series, \"tankNo\");\n\n      if (!valField) return;\n\n      const times = arr(timeField);\n      const vals = arr(valField);\n      const mins = arr(minField);\n      const maxs = arr(maxField);\n      const tanks = arr(tankField);\n\n      for (let i = 0; i < vals.length; i++) {\n        let tankNo = String(tanks[i] || \"\").toUpperCase();\n\n        if (!tankNo) {\n          tankNo = String(\n            valField.labels?.tankNo ||\n            valField.config?.displayNameFromDS ||\n            series.name ||\n            \"\"\n          ).toUpperCase();\n        }\n\n        const isAcid = valueKey.includes(\"acid\");\n        const isAlk = valueKey.includes(\"alkaline\");\n\n        if (tankNo === \"1\") tankNo = isAcid ? \"ACID1\" : isAlk ? \"ALK1\" : tankNo;\n        if (tankNo === \"2\") tankNo = isAcid ? \"ACID2\" : isAlk ? \"ALK2\" : tankNo;\n\n        if (tankNo.includes(\"ACID1\")) tankNo = \"ACID1\";\n        if (tankNo.includes(\"ACID2\")) tankNo = \"ACID2\";\n        if (tankNo.includes(\"ALK1\")) tankNo = \"ALK1\";\n        if (tankNo.includes(\"ALK2\")) tankNo = \"ALK2\";\n\n        if (!tankNo) continue;\n        if (!out[tankNo]) out[tankNo] = [];\n\n        out[tankNo].push({\n          time: times[i],\n          [valueKey]: vals[i],\n          [minKey]: mins[i],\n          [maxKey]: maxs[i]\n        });\n      }\n    });\n\n    return out;\n  }\n\n  function renderTrend(chartEl, lastEl, rows, valueKey, minKey, maxKey, cssLineClass, cssPointClass) {\n    if (!chartEl) return;\n\n    if (!rows.length) {\n      chartEl.innerHTML = \"\";\n      if (lastEl) lastEl.textContent = \"LAST: --\";\n      return;\n    }\n\n    const values = rows.map(r => Number(r[valueKey])).filter(Number.isFinite);\n    const mins = rows.map(r => Number(r[minKey])).filter(Number.isFinite);\n    const maxs = rows.map(r => Number(r[maxKey])).filter(Number.isFinite);\n\n    if (!values.length) {\n      chartEl.innerHTML = \"\";\n      if (lastEl) lastEl.textContent = \"LAST: --\";\n      return;\n    }\n\n    const last = values[values.length - 1];\n    const min = mins.length ? mins[mins.length - 1] : Math.min(...values);\n    const max = maxs.length ? maxs[maxs.length - 1] : Math.max(...values);\n\n    if (lastEl) {\n      lastEl.textContent = `LAST: ${last.toFixed(2)}`;\n      lastEl.classList.toggle(\"danger\", Number.isFinite(min) && Number.isFinite(max) && (last < min || last > max));\n    }\n\n    let yMin = Math.min(...values, ...mins);\n    let yMax = Math.max(...values, ...maxs);\n    if (yMin === yMax) {\n      yMin -= 1;\n      yMax += 1;\n    }\n\n    const pad = (yMax - yMin) * 0.12;\n    yMin -= pad;\n    yMax += pad;\n\n    const x = i => 20 + (i / Math.max(1, rows.length - 1)) * 560;\n    const y = v => 165 - ((v - yMin) / (yMax - yMin)) * 130;\n\n    const pts = rows.map((r, i) => `${x(i)},${y(Number(r[valueKey]))}`).join(\" \");\n    const lastX = rows.length === 1 ? 300 : x(rows.length - 1);\n    const singleLine = rows.length === 1\n      ? `<line x1=\"20\" y1=\"${y(last)}\" x2=\"580\" y2=\"${y(last)}\" class=\"trend-line ${cssLineClass}\"/>`\n      : `<polyline points=\"${pts}\" class=\"trend-line ${cssLineClass}\" fill=\"none\"/>`;\n    const yHigh = y(max);\n    const yLow = y(min);\n\n    chartEl.innerHTML = `\n      <svg viewBox=\"0 0 600 190\" class=\"trend-svg\" preserveAspectRatio=\"none\">\n        <line x1=\"20\" y1=\"${yHigh}\" x2=\"580\" y2=\"${yHigh}\" class=\"limit-high\"/>\n        <text x=\"24\" y=\"${yHigh - 8}\" class=\"limit-label high-label\">HIGH ${Number.isFinite(max) ? max.toFixed(2) : \"\"}</text>\n\n        <line x1=\"20\" y1=\"${yLow}\" x2=\"580\" y2=\"${yLow}\" class=\"limit-low\"/>\n        <text x=\"24\" y=\"${yLow - 8}\" class=\"limit-label low-label\">LOW ${Number.isFinite(min) ? min.toFixed(2) : \"\"}</text>\n\n        ${singleLine}\n        <circle cx=\"${lastX}\" cy=\"${y(last)}\" r=\"4.5\" class=\"trend-point ${cssPointClass}\"/>\n      </svg>\n    `;\n  }\n\n  const trendCards = [...root.querySelectorAll(\".trend-card\")];\n\n  function trendByTitle(text) {\n    return trendCards.find(c =>\n      String(c.querySelector(\".trend-title\")?.textContent || \"\")\n        .toUpperCase()\n        .includes(text.toUpperCase())\n    );\n  }\n\n  const acidRows = buildRows(acidTrend, \"acid_current\", \"acid_min\", \"acid_max\");\n  const alkRows = buildRows(alkTrend, \"alkaline_current\", \"alkaline_min\", \"alkaline_max\");\n\n  const acidT1Trend = trendByTitle(\"DILUTED ACID T1\");\n  const acidT2Trend = trendByTitle(\"DILUTED ACID T2\");\n  const alkT1Trend = trendByTitle(\"DILUTED ALKALINE T1\");\n  const alkT2Trend = trendByTitle(\"DILUTED ALKALINE T2\");\n\n  \n\n  renderTrend(\n    acidT1Trend?.querySelector(\".trend-chart\"),\n    acidT1Trend?.querySelector(\".trend-last\"),\n    acidRows.ACID1 || [],\n    \"acid_current\", \"acid_min\", \"acid_max\",\n    \"acid-line\", \"acid-point\"\n  );\n\n  renderTrend(\n    acidT2Trend?.querySelector(\".trend-chart\"),\n    acidT2Trend?.querySelector(\".trend-last\"),\n    acidRows.ACID2 || [],\n    \"acid_current\", \"acid_min\", \"acid_max\",\n    \"acid-line\", \"acid-point\"\n  );\n\n  renderTrend(\n    alkT1Trend?.querySelector(\".trend-chart\"),\n    alkT1Trend?.querySelector(\".trend-last\"),\n    alkRows.ALK1 || [],\n    \"alkaline_current\", \"alkaline_min\", \"alkaline_max\",\n    \"alk-line\", \"alk-point\"\n  );\n\n  renderTrend(\n    alkT2Trend?.querySelector(\".trend-chart\"),\n    alkT2Trend?.querySelector(\".trend-last\"),\n    alkRows.ALK2 || [],\n    \"alkaline_current\", \"alkaline_min\", \"alkaline_max\",\n    \"alk-line\", \"alk-point\"\n  );\n\n  renderCAAAlarms();\n\n} catch (err) {\n  console.log(\"CAA detail dashboard render error:\", err);\n}",
        "overflow": "visible",
        "panelupdateOnMount": true,
        "reduceOptions": {
          "calcs": [
            "lastNotNull",
            "last",
            "firstNotNull",
            "first",
            "min",
            "max",
            "mean",
            "sum",
            "count",
            "range",
            "delta",
            "step",
            "diff",
            "logmin",
            "allIsZero",
            "allIsNull",
            "diffperc"
          ]
        },
        "renderOnMount": true,
        "rootCSS": "",
        "useGrafanaScrollbar": true
      },
      "pluginVersion": "2.2.1",
      "targets": [
        {
          "datasource": {
            "type": "influxdb",
            "uid": "bfm1e64dc8lq8b"
          },
          "query": "SELECT LAST(\"processValue\") AS \"acid_current\",\nLAST(\"LCL\") AS \"acid_min\",\nLAST(\"UCL\") AS \"acid_max\",\nLAST(\"status\") AS \"status\"\nFROM \"caaChemicalStatusMain\"\nWHERE \"plantNo\" = '$plantNo'\nAND \"chemicalType\" = 'ACID'\nAND $timeFilter\nGROUP BY \"tankNo\"",
          "rawQuery": true,
          "refId": "A",
          "resultFormat": "table"
        },
        {
          "datasource": {
            "type": "influxdb",
            "uid": "bfm1e64dc8lq8b"
          },
          "hide": false,
          "query": "SELECT \"processValue\" AS \"acid_current\",\n\"LCL\" AS \"acid_min\",\n\"UCL\" AS \"acid_max\"\nFROM \"caaChemicalStatusMain\"\nWHERE \"plantNo\" = '$plantNo'\nAND \"chemicalType\" = 'ACID'\nAND $timeFilter\nGROUP BY \"tankNo\"\nORDER BY time ASC",
          "rawQuery": true,
          "refId": "B",
          "resultFormat": "table"
        },
        {
          "datasource": {
            "type": "influxdb",
            "uid": "bfm1e64dc8lq8b"
          },
          "hide": false,
          "query": "SELECT LAST(\"processValue\") AS \"alkaline_current\",\nLAST(\"LCL\") AS \"alkaline_min\",\nLAST(\"UCL\") AS \"alkaline_max\",\nLAST(\"status\") AS \"status\"\nFROM \"caaChemicalStatusMain\"\nWHERE \"plantNo\" = '$plantNo'\nAND \"chemicalType\" = 'ALKALINE'\nAND $timeFilter\nGROUP BY \"tankNo\"",
          "rawQuery": true,
          "refId": "C",
          "resultFormat": "table"
        },
        {
          "datasource": {
            "type": "influxdb",
            "uid": "bfm1e64dc8lq8b"
          },
          "hide": false,
          "query": "SELECT \"processValue\" AS \"alkaline_current\",\n\"LCL\" AS \"alkaline_min\",\n\"UCL\" AS \"alkaline_max\"\nFROM \"caaChemicalStatusMain\"\nWHERE \"plantNo\" = '$plantNo'\nAND \"chemicalType\" = 'ALKALINE'\nAND $timeFilter\nGROUP BY \"tankNo\"\nORDER BY time ASC",
          "rawQuery": true,
          "refId": "D",
          "resultFormat": "table"
        },
        {
          "datasource": {
            "type": "influxdb",
            "uid": "bfm1e64dc8lq8b"
          },
          "hide": false,
          "query": "SELECT LAST(\"value\") AS \"value\"\nFROM \"caaLevelPressureStatusDetailed\"\nWHERE \"plantNo\" = '$plantNo'\nAND $timeFilter\nGROUP BY \"item\"",
          "rawQuery": true,
          "refId": "E",
          "resultFormat": "table"
        }
      ],
      "title": "",
      "type": "gapit-htmlgraphics-panel"
    }
  ],
  "preload": false,
  "refresh": "15m",
  "schemaVersion": 41,
  "tags": [],
  "templating": {
    "list": [
      {
        "current": {
          "text": "2",
          "value": "2"
        },
        "label": "Plant",
        "name": "plantNo",
        "options": [
          {
            "selected": false,
            "text": "1",
            "value": "1"
          },
          {
            "selected": true,
            "text": "2",
            "value": "2"
          },
          {
            "selected": false,
            "text": "3",
            "value": "3"
          },
          {
            "selected": false,
            "text": "4",
            "value": "4"
          },
          {
            "selected": false,
            "text": "5",
            "value": "5"
          },
          {
            "selected": false,
            "text": "6",
            "value": "6"
          },
          {
            "selected": false,
            "text": "7",
            "value": "7"
          },
          {
            "selected": false,
            "text": "8",
            "value": "8"
          },
          {
            "selected": false,
            "text": "9",
            "value": "9"
          }
        ],
        "query": "1,2,3,4,5,6,7,8,9",
        "type": "custom"
      }
    ]
  },
  "time": {
    "from": "now-6h",
    "to": "now"
  },
  "timepicker": {},
  "timezone": "browser",
  "title": "All plant CAA Dashboard",
  "uid": "pr8kmwe",
  "version": 7
}